molecule_azure/__init__.py
molecule_azure/driver.py
molecule_azure/cookiecutter/cookiecutter.json
molecule_azure/cookiecutter/{{cookiecutter.molecule_directory}}/{{cookiecutter.scenario_name}}/INSTALL.rst
molecule_azure/cookiecutter/{{cookiecutter.molecule_directory}}/{{cookiecutter.scenario_name}}/converge.yml
molecule_azure/cookiecutter/{{cookiecutter.molecule_directory}}/{{cookiecutter.scenario_name}}/create.yml
molecule_azure/cookiecutter/{{cookiecutter.molecule_directory}}/{{cookiecutter.scenario_name}}/destroy.yml
molecule_azure/test/__init__.py
molecule_azure/test/test_driver.py
molecule_azure/test/functional/__init__.py
molecule_azure/test/functional/conftest.py
molecule_azure/test/functional/test_azure.py
molecule_azure/test/scenarios/driver/azure/molecule/default/converge.yml
molecule_azure/test/scenarios/driver/azure/molecule/default/molecule.yml
molecule_azure/test/scenarios/driver/azure/molecule/default/tests/test_default.py
molecule_azure/test/scenarios/driver/azure/molecule/multi-node/converge.yml
molecule_azure/test/scenarios/driver/azure/molecule/multi-node/molecule.yml
molecule_azure/test/scenarios/driver/azure/molecule/multi-node/prepare.yml
molecule_azure/test/scenarios/driver/azure/molecule/multi-node/tests/__init__.py
molecule_azure/test/scenarios/driver/azure/molecule/multi-node/tests/test_default.py
molecule_azure-0.5.0.dist-info/LICENSE
molecule_azure-0.5.0.dist-info/METADATA
molecule_azure-0.5.0.dist-info/WHEEL
molecule_azure-0.5.0.dist-info/entry_points.txt
molecule_azure-0.5.0.dist-info/top_level.txt
molecule_azure-0.5.0.dist-info/RECORD
