Metadata-Version: 2.1
Name: molecule-azure
Version: 0.5.0
Summary: Azure Molecule Plugin :: run molecule tests on Azure
Home-page: https://github.com/ansible-community/molecule-azure
Author: Sorin Sbarnea
Author-email: sorin.sbarnea@gmail.com
Maintainer: Sorin Sbarnea
Maintainer-email: sorin.sbarnea@gmail.com
License: MIT
Project-URL: Bug Tracker, https://github.com/ansible-community/molecule-azure/issues
Project-URL: Release Management, https://github.com/ansible-community/molecule-azure/releases
Project-URL: CI, https://github.com/ansible-community/molecule-azure/actions
Project-URL: Documentation, https://molecule.readthedocs.io
Project-URL: Mailing lists, https://docs.ansible.com/ansible/latest/community/communication.html#mailing-list-information
Project-URL: Source Code, https://github.com/ansible-community/molecule-azure
Keywords: ansible,roles,testing,molecule,plugin,azure
Platform: UNKNOWN
Classifier: Development Status :: 5 - Production/Stable
Classifier: Environment :: Console
Classifier: Framework :: Pytest
Classifier: Intended Audience :: Developers
Classifier: Intended Audience :: Information Technology
Classifier: Intended Audience :: System Administrators
Classifier: License :: OSI Approved :: MIT License
Classifier: Natural Language :: English
Classifier: Operating System :: OS Independent
Classifier: Programming Language :: Python :: 3
Classifier: Programming Language :: Python :: 3.6
Classifier: Programming Language :: Python :: 3.7
Classifier: Programming Language :: Python :: 3.8
Classifier: Programming Language :: Python :: 3.9
Classifier: Topic :: System :: Systems Administration
Classifier: Topic :: Utilities
Requires-Python: >=3.6
Requires-Dist: molecule (>=3.2.0a0)
Provides-Extra: test
Requires-Dist: molecule[ansible,test] ; extra == 'test'
